antlib/__init__.py
antlib/antdefines.py
antlib/antdevice.py
antlib/antmessage.py
antlib-1.0b0.data/data/lib/site-packages/antlib/ANT_WrappedLib.dll
antlib-1.0b0.data/data/lib/site-packages/antlib/DSI_CP210xManufacturing_3_1.dll
antlib-1.0b0.data/data/lib/site-packages/antlib/DSI_SiUSBXp_3_1.dll
antlib-1.0b0.data/data/lib/site-packages/antlib/LICENSE
antlib-1.0b0.dist-info/LICENSE
antlib-1.0b0.dist-info/METADATA
antlib-1.0b0.dist-info/WHEEL
antlib-1.0b0.dist-info/top_level.txt
antlib-1.0b0.dist-info/RECORD
