Metadata-Version: 2.1
Name: antlib
Version: 1.0b0
Summary: A python wrapper for the ant library
Home-page: http://thisisant.com
Maintainer: Garmin Canada Ant Wireless Team
Maintainer-email: opensource@thisisant.com
License: Apache License, Version 2.0
Platform: UNKNOWN
Classifier: Development Status :: 4 - Beta
Classifier: Intended Audience :: Developers
Classifier: Programming Language :: Python :: 2.7
Classifier: Programming Language :: Python :: 3.7
Classifier: Operating System :: Microsoft :: Windows
Classifier: License :: OSI Approved :: Apache Software License
Classifier: Topic :: Software Development :: Embedded Systems
Classifier: Topic :: System :: Networking
